resqml201/__init__.py
resqml201/absorbed_dose_measure.py
resqml201/absorbed_dose_uom.py
resqml201/abstract_activity_parameter.py
resqml201/abstract_boolean_array.py
resqml201/abstract_cited_data_object.py
resqml201/abstract_column_layer_grid_geometry.py
resqml201/abstract_column_layer_grid_representation.py
resqml201/abstract_contact_interpretation_part.py
resqml201/abstract_contact_representation_part.py
resqml201/abstract_contextual_object.py
resqml201/abstract_coordinate_operation_type.py
resqml201/abstract_coordinate_system_type.py
resqml201/abstract_data_object.py
resqml201/abstract_double_array.py
resqml201/abstract_dq_element_type.py
resqml201/abstract_dq_positional_accuracy_type.py
resqml201/abstract_dq_result_type.py
resqml201/abstract_ex_geographic_extent_type.py
resqml201/abstract_feature.py
resqml201/abstract_feature_interpretation.py
resqml201/abstract_general_conversion_type.py
resqml201/abstract_geologic_feature.py
resqml201/abstract_geometry.py
resqml201/abstract_gmltype.py
resqml201/abstract_grid_geometry.py
resqml201/abstract_grid_representation.py
resqml201/abstract_integer_array.py
resqml201/abstract_local3d_crs.py
resqml201/abstract_object.py
resqml201/abstract_object_type.py
resqml201/abstract_organization_interpretation.py
resqml201/abstract_parameter_key.py
resqml201/abstract_parametric_line_array.py
resqml201/abstract_parametric_line_geometry.py
resqml201/abstract_parent_window.py
resqml201/abstract_plane_geometry.py
resqml201/abstract_point3d_array.py
resqml201/abstract_projected_crs.py
resqml201/abstract_property.py
resqml201/abstract_property_kind.py
resqml201/abstract_property_lookup.py
resqml201/abstract_representation.py
resqml201/abstract_resqml_data_object.py
resqml201/abstract_seismic_coordinates.py
resqml201/abstract_seismic_survey_feature.py
resqml201/abstract_stratigraphic_organization_interpretation.py
resqml201/abstract_surface_framework_representation.py
resqml201/abstract_surface_representation.py
resqml201-1.0.0.dist-info/LICENSE
resqml201-1.0.0.dist-info/WHEEL
resqml201-1.0.0.dist-info/METADATA
resqml201-1.0.0.dist-info/RECORD
